AUTHORS.rst
CONTRIBUTING.rst
HISTORY.rst
Makefile
docs/Makefile
docs/authors.rst
docs/conf.py
docs/contributing.rst
docs/history.rst
docs/index.rst
docs/installation.rst
docs/make.bat
docs/readme.rst
docs/usage.rst
ip_liberator/__init__.py
ip_liberator/__main__.py
ip_liberator/ip_liberator.py
ip_liberator/utils.py
ip_liberator-0.2.4.dist-info/entry_points.txt
ip_liberator-0.2.4.dist-info/LICENSE
ip_liberator-0.2.4.dist-info/WHEEL
ip_liberator-0.2.4.dist-info/METADATA
ip_liberator-0.2.4.dist-info/RECORD
