Metadata-Version: 2.1
Name: ip-liberator
Version: 0.2.4
Summary: A command line utility to update AWS Security Groups rules.
Home-page: https://github.com/wagnerluis1982/ip-liberator
License: GPL-3.0
Keywords: ip-liberator,Python,Amazon AWS,cloud computing,DevOps
Author: Wagner Macedo
Author-email: wagnerluis1982@gmail.com
Requires-Python: >=3.6,<4.0
Classifier: Development Status :: 4 - Beta
Classifier: Environment :: Console
Classifier: Intended Audience :: Developers
Classifier: Intended Audience :: End Users/Desktop
Classifier: License :: OSI Approved :: GNU General Public License v3 (GPLv3)
Classifier: Natural Language :: English
Classifier: Operating System :: POSIX :: Linux
Classifier: Programming Language :: Python :: 3
Classifier: Programming Language :: Python :: 3.6
Classifier: Programming Language :: Python :: 3.7
Classifier: Topic :: Utilities
Requires-Dist: boto3 (==1.9.133)
Project-URL: Documentation, https://ip-liberator.readthedocs.io
Project-URL: Repository, https://github.com/wagnerluis1982/ip-liberator
